[
    {
        "condition": "预防措施",
        "variable": "砌体结构破坏",
        "probabilities": {
            "不采取": {
                "发生": "very likely"
            }
        }
    },
    {
        "condition": "地基土类型",
        "variable": "胀缩变形幅度",
        "probabilities": {
            "膨胀土": {
                "10mm～20mm": "high",
                "小于10mm": "low",
                "大于20mm": "low"
            },
            "非膨胀土": {
                "10mm～20mm": "low",
                "小于10mm": "high",
                "大于20mm": "low"
            }
        }
    }
]