[{"variable_name": "排水工程设施", "variable_type": "chance", "values": ["排水管网", "提升泵房", "污水处理厂"]}, {"variable_name": "地震破坏", "variable_type": "chance", "values": ["系统遭受地震破坏", "系统未遭受地震破坏"]}, {"variable_name": "环境污染", "variable_type": "chance", "values": ["环境污染", "无环境污染"]}, {"variable_name": "传染病", "variable_type": "chance", "values": ["引发传染病", "未引发传染病"]}, {"variable_name": "污水处理厂运行", "variable_type": "decision", "values": ["基本正常运行", "无法正常运行"]}, {"variable_name": "排水管网损坏", "variable_type": "chance", "values": ["损坏引发次生灾害", "损坏未引发次生灾害"]}, {"variable_name": "污水处理池破坏", "variable_type": "chance", "values": ["大容量污水处理池破坏", "大容量污水处理池未破坏"]}, {"variable_name": "污水泛滥", "variable_type": "chance", "values": ["数以万吨计的污水泛滥", "无污水泛滥"]}, {"variable_name": "修复困难", "variable_type": "chance", "values": ["修复困难", "修复容易"]}, {"variable_name": "后果严重", "variable_type": "chance", "values": ["后果严重", "后果不严重"]}]