[{"variable_name": "异形柱结构设计与施工问题", "variable_type": "chance", "values": []}, {"variable_name": "异形柱结构的国家和行业标准", "variable_type": "decision", "values": ["补充完善", "未涉及"]}, {"variable_name": "异形柱结构基本性能研究", "variable_type": "decision", "values": ["进行", "未进行"]}, {"variable_name": "异形柱结构设计方法研究", "variable_type": "decision", "values": ["进行", "未进行"]}, {"variable_name": "异形柱结构构造措施研究", "variable_type": "decision", "values": ["进行", "未进行"]}, {"variable_name": "异形柱结构工程应用研究", "variable_type": "decision", "values": ["进行", "未进行"]}, {"variable_name": "异形柱结构模型试验研究", "variable_type": "decision", "values": ["进行", "未进行"]}, {"variable_name": "异形柱结构抗震分析及性能研究", "variable_type": "decision", "values": ["进行", "未进行"]}, {"variable_name": "异形柱结构专用设计软件研究", "variable_type": "decision", "values": ["进行", "未进行"]}, {"variable_name": "异形柱结构标准设计研究", "variable_type": "decision", "values": ["进行", "未进行"]}, {"variable_name": "异形柱结构地方标准制定与实施", "variable_type": "decision", "values": ["已制定并实施", "未制定"]}, {"variable_name": "异形柱结构住宅建筑建设", "variable_type": "decision", "values": ["已建设", "未建设"]}, {"variable_name": "国家行业标准《混凝土异形柱结构技术规程》JGJ编制", "variable_type": "decision", "values": ["已组织编制", "未组织编制"]}]