[{"variable_name": "挡土结构", "variable_type": "decision", "values": ["挡土墙", "地下室外墙", "基坑支护结构"]}, {"variable_name": "水平膨胀力", "variable_type": "chance", "values": ["作用于挡土结构"]}, {"variable_name": "土的成因类型和矿物组成", "variable_type": "chance", "values": ["不同导致竖向膨胀率与固结仪上测得数值的差异"]}, {"variable_name": "土中矿物颗粒排列", "variable_type": "chance", "values": ["片状水平排列时土的竖向膨胀潜势大于横向"]}, {"variable_name": "土的三向膨胀性能", "variable_type": "chance", "values": ["线膨胀率和体膨胀率随土的密度增大和初始含水量减小而增大", "压力是抑制膨胀变形的主要因素"]}, {"variable_name": "土样", "variable_type": "chance", "values": ["原状膨胀土样", "黑棉土", "粉色膨胀土"]}, {"variable_name": "试验研究", "variable_type": "decision", "values": ["在三轴仪上进行", "在改进的三轴仪上进行"]}, {"variable_name": "膨胀土的膨胀率", "variable_type": "chance", "values": ["竖向膨胀率比固结仪上测得的数值小", "竖向膨胀比横向膨胀大或相反"]}, {"variable_name": "土的密度和初始含水量", "variable_type": "chance", "values": ["影响膨胀土的三向膨胀性能"]}, {"variable_name": "压力", "variable_type": "chance", "values": ["影响膨胀土的膨胀变形"]}]